spectrum_basic/__init__.py
spectrum_basic/__main__.py
spectrum_basic/ast.py
spectrum_basic/ast_base.py
spectrum_basic/core.py
spectrum_basic/gen_ast.py
spectrum_basic/run.py
spectrum_basic/spectrum_basic.tx
spectrum_basic/tokenizer.py
spectrum_basic/zxinput.py
spectrum_basic/zxoutput.py
spectrum_basic-0.6.7.dist-info/METADATA
spectrum_basic-0.6.7.dist-info/WHEEL
spectrum_basic-0.6.7.dist-info/entry_points.txt
spectrum_basic-0.6.7.dist-info/top_level.txt
spectrum_basic-0.6.7.dist-info/RECORD
