Metadata-Version: 2.4
Name: spectrum-basic
Version: 0.6.7
Summary: A parser and language tool for ZX Spectrum BASIC
Author-email: "Melissa E. O'Neill" <oneill@acm.org>
License: MIT
Project-URL: Homepage, https://github.com/imneme/spectrum-basic
Project-URL: Documentation, https://github.com/imneme/spectrum-basic#readme
Project-URL: Bug Tracker, https://github.com/imneme/spectrum-basic/issues
Keywords: zx-spectrum,basic,retro,compiler
Classifier: Development Status :: 4 - Beta
Classifier: Environment :: Console
Classifier: Intended Audience :: Developers
Classifier: License :: OSI Approved :: MIT License
Classifier: Programming Language :: Python :: 3.10
Classifier: Topic :: Software Development :: Compilers
Classifier: Topic :: Software Development :: Libraries :: Python Modules
Requires-Python: >=3.10
Requires-Dist: textx
